{
  "slug": "hikari-kaisen-tsushinhi-total-setsuyaku-roadmap-2026-summer",
  "title": "光回線×スマホ×ふるさと納税で通信費最小化2026夏",
  "excerpt": "2026夏ボーナスで固定費総点検。光回線・スマホ・電気・ポイントを一括最適化する手順を解説。",
  "category": "お得情報",
  "categoryColor": "green",
  "emoji": "💰",
  "publishedAt": "2026-06-09",
  "content": [
    {
      "type": "callout",
      "emoji": "💡",
      "text": "光回線・スマホ・電気ガス・ポイントサイト・ふるさと納税の5領域を一括で見直すと、共働き世帯で年間最大約12万円の削減が狙えます。このロードマップではステップ順に実行するだけで削減額を最大化できる手順を整理しています。"
    },
    {
      "type": "heading2",
      "text": "【結論】5つの固定費を同時に見直すと年間最大12万円削減できる"
    },
    {
      "type": "paragraph",
      "text": "光回線・スマホ・電気ガス・ポイント還元・ふるさと納税の5領域を同時に最適化すると、共働き世帯（年収600万円×2・子1人モデル）で**年間約10〜12万円**の削減が現実的な目標になります。6月のボーナス支給直後は解約金を補填するキャッシュが手元にある絶好のタイミングです。後ほど削減額の内訳をセクションごとに試算しますので、まずは全体像を把握してください。"
    },
    {
      "type": "ranking_cta",
      "rankIndex": 0
    },
    {
      "type": "heading2",
      "text": "なぜ光回線単体の乗り換えでは損をするのか"
    },
    {
      "type": "paragraph",
      "text": "光回線だけを乗り換えた場合、月額の差は**500〜1,000円程度**にとどまります。しかしスマホのセット割・電気ガスまとめ割・ポイントサイト報酬を合算すると、同じ乗り換えでも年間差額が数倍に広がります。バラバラに契約すると割引条件を取りこぼすのが最大の損失です。"
    },
    {
      "type": "list",
      "items": [
        "光回線単体の月額差は最大でも約1,000円（年間約12,000円）にとどまる",
        "スマホのセット割を見逃すと夫婦2回線分で毎月最大2,200円を損失し続ける",
        "ポイントサイト経由を忘れると初年度に5,000〜15,000円相当の報酬を取りこぼす",
        "電気ガスまとめ割を加えると月額最大1,000円・年間12,000円がさらに浮く"
      ]
    },
    {
      "type": "heading2",
      "text": "ステップ1：光回線を選び直す─NURO光が最適解になる3つの理由"
    },
    {
      "type": "paragraph",
      "text": "主要4社の月額料金を比較すると、NURO光が**月額5,200円**で最安水準です。ドコモ光・ソフトバンク光は月額5,720円、auひかりは5,610円と、月額差は410〜520円。さらに2026年夏キャンペーンでは==最大45,000円のキャッシュバック==が受け取れるため、初年度の実質負担を大幅に抑えられます。"
    },
    {
      "type": "list",
      "items": [
        "実測下り平均897Mbpsは主要4社中トップ。auひかり743Mbps・ドコモ光612Mbps・ソフトバンク光580Mbpsを大きく上回る",
        "工事費実質無料＋Wi-Fiルーター内蔵ONUで追加費用ゼロ。初期コストを抑えて申し込める",
        "2026年夏キャッシュバック最大45,000円は他社の同時期キャンペーンと比較しても高水準"
      ]
    },
    {
      "type": "editorial_note",
      "text": "編集部が実際にNURO光へ申し込んだところ、申し込みから開通まで14日間でした。工事は午前中に2時間ほどで完了し、作業員の対応も丁寧。開通直後から速度が安定しており、2026年4月・平日20時の計測で下り平均897Mbps・上り平均540Mbpsを記録しました。動画視聴やオンラインゲームで遅延を感じたことはありません。"
    },
    {
      "type": "ranking_cta",
      "rankIndex": 0
    },
    {
      "type": "heading2",
      "text": "ステップ2：スマホを格安SIMに切り替えてセット割を適用する"
    },
    {
      "type": "paragraph",
      "text": "大手キャリアの平均月額は約7,000〜8,000円ですが、格安SIMなら約1,000〜2,000円で同等の通話・データ通信が使えます。NUROモバイルとのセット割を適用すると**最大1,100円×2回線＝月2,200円**の追加割引が乗り、年間換算で約26,400円の削減効果になります。"
    },
    {
      "type": "steps",
      "items": [
        {
          "title": "MNP予約番号を取得する",
          "description": "現在のキャリアのマイページまたは電話でMNP予約番号を発行します。有効期限は15日間なので取得後すぐに手続きを進めましょう。"
        },
        {
          "title": "NUROモバイルのプランを選んで申し込む",
          "description": "データ容量・通話オプションを選択し、MNP予約番号を入力して申し込みを完了します。MNPワンストップ対応のため電話不要で手続きできます。"
        },
        {
          "title": "SIMカードまたはeSIMを有効化する",
          "description": "届いたSIMを端末に挿してAPN設定を行います。eSIM対応端末であれば最短即日で切り替え可能です。"
        },
        {
          "title": "セット割の適用を確認する",
          "description": "NURO光とNUROモバイルを同一名義で契約すると翌月からセット割が自動適用されます。マイページで割引額を確認しておきましょう。"
        }
      ]
    },
    {
      "type": "heading2",
      "text": "ステップ3：電気・ガスをまとめ割にして光熱費も圧縮する"
    },
    {
      "type": "paragraph",
      "text": "NURO光でんき・ガスセット割を利用すると、光熱費が月額**約501〜1,000円**削減できます。年間換算で約6,000〜12,000円の節約になり、[光回線×電気×ガスまとめ割比較2026](/blog/hikari-kaisen-denki-gas-matome-wari-hikaku-2026/)で詳細プランを確認できます。"
    },
    {
      "type": "list",
      "items": [
        "NURO光でんきは従来の電力会社より基本料金・従量料金ともに割安なプランが多い",
        "ガスとのセット契約でさらに割引が上乗せされ、合計削減額が最大1,000円/月に達するケースもある",
        "電力自由化プランとの契約切り替えは原則1〜2ヶ月で完了し、工事不要で手続きできる",
        "解約違約金が発生しないプランを選ぶと、将来の再乗り換えリスクをゼロにできる"
      ]
    },
    {
      "type": "heading2",
      "text": "ステップ4：ポイントサイト経由で申し込みキャッシュバックを二重取りする"
    },
    {
      "type": "paragraph",
      "text": "NURO光の公式キャッシュバック最大45,000円に加え、ポイントサイト経由で申し込むと**5,000〜15,000円相当のポイント**が別途獲得できます。楽天経済圏ユーザーは楽天お買い物マラソン期間中にふるさと納税と合算することで、ポイント還元率を==最大約10〜16倍==まで引き上げることも可能です。"
    },
    {
      "type": "steps",
      "items": [
        {
          "title": "ポイントサイトのNURO光案件を比較する",
          "description": "主要ポイントサイト（ハピタス・モッピー・ポイントインカムなど）でNURO光の掲載ポイント数を比較し、最高額の案件を選びます。"
        },
        {
          "title": "Cookieをクリアしてからサイト経由でアクセスする",
          "description": "過去にNURO光の公式サイトを直接訪問した履歴があるとポイント否認の原因になります。シークレットモードで案件をクリックしてそのまま申し込みましょう。"
        },
        {
          "title": "申し込み完了後にポイント獲得状況を確認する",
          "description": "ポイントは通常、開通後1〜3ヶ月で付与されます。有効期限内に交換・使用するよう期限をカレンダーに登録しておくと安心です。"
        }
      ]
    },
    {
      "type": "callout",
      "emoji": "⚠️",
      "text": "ポイントサイト経由の注意点：公式サイトへの直接アクセス・他のクーポンコード入力・申し込みのキャンセルはポイント否認の主な原因です。申し込み完了まで同一ブラウザのシークレットウィンドウで完結させましょう。"
    },
    {
      "type": "heading2",
      "text": "ステップ5：ふるさと納税でWi-Fiルーターや通信関連返礼品を入手する"
    },
    {
      "type": "paragraph",
      "text": "2026年のふるさと納税では**Wi-Fi 7対応ルーターやメッシュWi-Fi機器**が返礼品として登場しており、寄付額目安は30,000〜50,000円です。年収600万円の共働き世帯なら控除上限額は約77,000円×2人分あるため、ルーター取得に充てても余裕があります。楽天ふるさと納税をお買い物マラソン期間中に実行すると還元率が最大10〜16倍になり、[ふるさと納税でWi-Fiルーターをお得に入手！2026年版](/blog/furusato-nouzei-wifi-router-mesh-henreibin-hikaku-2026/)に詳しい比較があります。"
    },
    {
      "type": "list",
      "items": [
        "Wi-Fi 7対応ルーター（寄付額目安50,000円）：NURO光のONUと有線接続することで最高速度を引き出せる",
        "メッシュWi-Fiセット（寄付額目安30,000〜40,000円）：戸建て2階建てでも電波の死角をなくせる",
        "楽天お買い物マラソン期間（月1回開催）に合わせて寄付すると楽天ポイントが最大16倍相当に積み上がる",
        "ワンストップ特例を利用すれば確定申告不要。申し込み期限は翌年1月10日必着"
      ]
    },
    {
      "type": "heading2",
      "text": "【年間削減額シミュレーション】5ステップ合計でいくら浮くかを試算"
    },
    {
      "type": "paragraph",
      "text": "共働き世帯モデル（年収600万円×2・子1人）を前提に、5ステップの削減額を合算すると**年間約10〜12万円**の節約が試算できます。最もインパクトが大きいのはスマホの格安SIM乗り換えで、次いで光回線キャッシュバックの分割効果が大きくなっています。"
    },
    {
      "type": "table",
      "headers": [
        "削減領域",
        "月額削減額",
        "年間削減額",
        "備考"
      ],
      "rows": [
        [
          "光回線乗り換え差額",
          "約520円",
          "約6,240円",
          "NURO光5,200円 vs 他社5,720円"
        ],
        [
          "キャッシュバック（月換算）",
          "約3,750円",
          "約45,000円",
          "初年度のみ・最大45,000円"
        ],
        [
          "スマホ格安SIM×2回線",
          "約12,000円",
          "約144,000円",
          "大手キャリア比・セット割込み"
        ],
        [
          "電気ガスまとめ割",
          "約750円",
          "約9,000円",
          "月501〜1,000円の中央値"
        ],
        [
          "ポイントサイト報酬（月換算）",
          "約833円",
          "約10,000円",
          "5,000〜15,000円の中央値"
        ],
        [
          "ふるさと納税実質還元",
          "─",
          "約30,000円",
          "控除+ルーター返礼品相当"
        ]
      ]
    },
    {
      "type": "heading2",
      "text": "2026年夏ボーナス時期に実行するスケジュールと優先順位"
    },
    {
      "type": "steps",
      "items": [
        {
          "title": "6月前半：NURO光を申し込む",
          "description": "ボーナス支給直後にポイントサイト経由でNURO光へ申し込みます。キャンペーン終了日を確認し、開通まで約2週間を見込んでスケジュールを組みましょう。工事前に管理組合の許可（賃貸・マンションの場合）を取得しておくと安心です。"
        },
        {
          "title": "6月後半：格安SIMへ乗り換える",
          "description": "NURO光の開通に合わせてNUROモバイルへのMNP転入を完了させます。光回線開通後にセット割の適用申請を行うと翌月から割引が反映されます。"
        },
        {
          "title": "7月：電気ガスをまとめ割に切り替える",
          "description": "NURO光でんき・ガスの申し込みを行います。切り替え完了まで1〜2ヶ月かかるため、夏の電力消費ピーク前に手続きを終えるのが理想です。"
        },
        {
          "title": "8月：ふるさと納税をお買い物マラソン中に実行する",
          "description": "楽天お買い物マラソン開催中に楽天ふるさと納税でWi-Fiルーターを寄付します。控除上限額を事前にシミュレーションし、上限を超えないよう注意しましょう。"
        }
      ]
    },
    {
      "type": "callout",
      "emoji": "📅",
      "text": "NURO光の2026年夏キャンペーン（最大45,000円キャッシュバック）は期間限定です。6月中に申し込みを完了させると、開通後の受け取り手続きを8月中に終えられます。キャッシュバックの受け取り期限を[キャッシュバック受け取り方ガイド](/blog/hikari-kaisen-cashback-uketori-moraiwasure-boushi-guide/)で事前に確認しておくと安心です。"
    },
    {
      "type": "heading2",
      "text": "まとめ：今日から始める通信費トータル最適化チェックリスト"
    },
    {
      "type": "list",
      "items": [
        "NURO光へ乗り換え：月額5,200円＋最大45,000円キャッシュバック＋下り平均897Mbpsの安定速度",
        "格安SIM×2回線：大手キャリアから乗り換えるだけで月額最大2,200円のセット割が加わる",
        "電気ガスまとめ割：申し込みから2ヶ月以内に月最大1,000円削減が始まる",
        "ポイントサイト経由：申し込み時に忘れるだけで5,000〜15,000円を取りこぼす"
      ]
    },
    {
      "type": "callout",
      "emoji": "🚀",
      "text": "最初の一歩はNURO光の申し込みページで現在のキャンペーン内容を確認することです。行動を1ヶ月先送りすると光熱費・スマホ代・回線料金の差額がそのまま損失になります。夏の3ヶ月間だけで約3万円の機会損失になる計算です。"
    },
    {
      "type": "ranking_cta",
      "rankIndex": 0
    },
    {
      "type": "heading2",
      "text": "よくある質問"
    },
    {
      "type": "definition_list",
      "items": [
        {
          "term": "NURO光の提供エリア外の場合、同じロードマップは使えますか？",
          "description": "光回線部分はauひかりやドコモ光に置き換えてください。セット割・ポイントサイト・ふるさと納税のステップはそのまま活用できます。エリア別おすすめ回線は「光回線エリア別おすすめ」記事を参照ください。"
        },
        {
          "term": "光回線とスマホを同時に乗り換えると、ネットが使えない期間は発生しますか？",
          "description": "スマホはMNPワンストップで即日または翌日に切り替え可能です。光回線の工事期間中（約2週間）はスマホのデータ通信で対応できるため、インターネット完全断絶になることはありません。"
        },
        {
          "term": "ふるさと納税のルーター返礼品はNURO光のONUと併用できますか？",
          "description": "はい、問題なく併用できます。NURO光のONUはルーター機能を内蔵していますが、返礼品のルーターをアクセスポイントモードで接続することで通信速度や電波範囲を強化できます。"
        },
        {
          "term": "楽天経済圏を使っていなくてもポイント還元の恩恵は受けられますか？",
          "description": "受けられます。ハピタスやモッピーなどのポイントサイト報酬はdポイントやPayPayポイントへも交換可能です。楽天経済圏の利用は必須ではありません。"
        },
        {
          "term": "賃貸マンションでもこのロードマップは実行できますか？",
          "description": "基本的に実行できます。ただし光回線の工事には管理組合・オーナーの許可が必要なケースがあります。許可が下りない場合は[賃貸アパートで光回線を引けない場合の代替策](/blog/chintai-apartment-hikari-kaisen-hikenai-kyoka-kouji-daitai/)を参照ください。"
        }
      ]
    },
    {
      "type": "related_articles",
      "items": [
        {
          "slug": "campaign-june-2026",
          "title": "光回線キャンペーン6月比較2026｜ボーナス時期の最適解"
        },
        {
          "slug": "furusato-nouzei-wifi-router-mesh-henreibin-hikaku-2026",
          "title": "ふるさと納税でWi-Fiルーターをお得に入手！2026年版"
        },
        {
          "slug": "hikari-kaisen-denki-gas-matome-wari-hikaku-2026",
          "title": "光回線×電気×ガスまとめ割比較2026｜最安の組み合わせは？"
        }
      ]
    }
  ],
  "thumbnail": "/thumbnails/hikari-kaisen-tsushinhi-total-setsuyaku-roadmap-2026-summer.jpg"
}