{
  "slug": "hikari-karikae-iyakukin-sosonai",
  "title": "光回線の乗り換えで損しない！違約金の仕組みと対策",
  "excerpt": "光回線の乗り換えで発生する違約金の仕組みと、費用を抑えて損しない乗り換え方法をわかりやすく解説。",
  "category": "お得情報",
  "categoryColor": "orange",
  "emoji": "💡",
  "publishedAt": "2026-03-25",
  "content": [
    {
      "type": "callout",
      "emoji": "📋",
      "text": "この記事でわかること\n・光回線の違約金（解約金）が発生する仕組み\n・違約金を無料または最小限に抑える乗り換えのタイミング\n・乗り換え先が違約金を負担してくれるキャンペーンの活用法\n・費用負担ゼロで乗り換えられるケースの見分け方\n・乗り換え先として特におすすめの回線"
    },
    {
      "type": "heading2",
      "text": "光回線の乗り換えで最初に確認すること"
    },
    {
      "type": "paragraph",
      "text": "乗り換えを決めたなら、まず「いくらかかるか」を把握することが先決です。光回線の乗り換えにかかる費用は大きく3種類あり、これを整理するだけで「思ったより高かった」という後悔を防げます。現在の回線の**解約にかかる費用**、工事や撤去にかかる費用、そして乗り換え先の初期費用です。このうち金額が最も大きくなりやすいのが解約費用、いわゆる違約金です。"
    },
    {
      "type": "heading2",
      "text": "違約金（解約金）が発生する仕組みを理解する"
    },
    {
      "type": "paragraph",
      "text": "光回線の違約金は、==契約期間内に解約したときに発生するペナルティ==です。多くのプロバイダは「2年契約」「3年契約」といった縛りを設けており、その期間内に解約すると数千円〜数万円の費用が請求されます。2022年の電気通信事業法改正により、**違約金の上限は1,000円**と定められましたが、これは新規契約分に限った話です。改正前に契約した回線は旧ルールが適用され、10,000円前後の違約金が発生するケースがまだ残っています。"
    },
    {
      "type": "paragraph",
      "text": "また、違約金とは別に**光コラボ回線（フレッツ光を使ったプロバイダ）から別の光コラボへ乗り換える場合**は、事業者変更という手続きになるため撤去工事は不要です。一方、フレッツ光や光コラボからNURO光・auひかりのような独自回線へ移る場合は、元の回線の撤去工事費（実費）が別途かかる場合があります。契約中のサービスが何かを確認しておくと、費用の見積もりがぐっと楽になります。"
    },
    {
      "type": "definition_list",
      "items": [
        {
          "term": "違約金（解約違約金）",
          "description": "契約期間内に解約した場合に発生するペナルティ料金。2022年法改正後の新規契約は上限1,000円だが、改正前の契約には旧ルールが適用される。"
        },
        {
          "term": "光コラボ",
          "description": "NTTのフレッツ光回線を借りて提供するサービスの総称。ドコモ光・ソフトバンク光・BIGLOBE光などが該当する。"
        },
        {
          "term": "事業者変更",
          "description": "光コラボ同士で乗り換える手続き。工事不要で乗り換えられるため、撤去費用がかからない。"
        },
        {
          "term": "転用",
          "description": "フレッツ光からNTT系光コラボへ移行する手続き。こちらも工事不要。"
        },
        {
          "term": "新規工事（独自回線への乗り換え）",
          "description": "NURO光・auひかりなど独自回線への乗り換えは新規工事が必要。現回線の撤去費用と新規開通工事費の両方が発生する場合がある。"
        }
      ]
    },
    {
      "type": "heading2",
      "text": "損しない乗り換えの第一歩はNURO光の確認から"
    },
    {
      "type": "paragraph",
      "text": "現状の費用を把握したうえで比較するなら、乗り換え先の筆頭候補として**NURO光**を確認しておくことをおすすめします。実測平均速度は下り**897Mbps**で業界トップクラス、月額料金は戸建て向け「NURO光 forホーム」で**5,200円**（2年契約・税込）と、高速・安定・コスパを同時に実現しています。さらに現在は乗り換えユーザー向けのキャンペーンも展開中で、違約金の負担を軽減できる場合があります。"
    },
    {
      "type": "ranking_cta",
      "rankIndex": 0
    },
    {
      "type": "heading2",
      "text": "違約金を無料または最小限にする3つの方法"
    },
    {
      "type": "paragraph",
      "text": "費用を抑えて乗り換えるアプローチは主に3つあります。自分の状況に合ったものを選ぶと、実質的な負担をゼロに近づけられます。"
    },
    {
      "type": "list",
      "items": [
        "更新月に解約する：契約更新月（多くは契約満了月とその前後1〜2か月）に解約すると違約金が発生しない。マイページや問い合わせ窓口で更新月を必ず確認しておく。",
        "乗り換え先の「違約金補填キャンペーン」を使う：NURO光・auひかりなどは、他社解約費用を一定額まで負担するキャンペーンを定期的に実施している。申し込み時に申請が必要なケースが多いため見落とし注意。",
        "2022年改正後の契約かどうかを確認する：2022年7月以降に締結した契約なら違約金上限は1,000円。旧契約のままの場合は更新月待ちか補填キャンペーンの活用が現実的。"
      ]
    },
    {
      "type": "heading2",
      "text": "乗り換え先3社を費用・速度・特徴で比較"
    },
    {
      "type": "paragraph",
      "text": "乗り換え先を選ぶときは、月額料金だけでなく**実際の速度・エリア・スマホとのセット割**を合わせて確認するのが重要です。以下の表に主要3社の主要スペックをまとめています。"
    },
    {
      "type": "table",
      "headers": [
        "項目",
        "NURO光",
        "auひかり",
        "ドコモ光"
      ],
      "rows": [
        [
          "月額料金（戸建て）",
          "5,200円〜",
          "5,610円〜",
          "5,720円〜"
        ],
        [
          "最大通信速度",
          "10Gbps",
          "1Gbps（一部10Gbps）",
          "1Gbps"
        ],
        [
          "実測平均（下り）",
          "897Mbps",
          "743Mbps",
          "682Mbps"
        ],
        [
          "回線の種類",
          "独自回線",
          "独自回線",
          "光コラボ（フレッツ）"
        ],
        [
          "スマホ割",
          "ソフトバンク・LINEMOなど",
          "au・UQ mobile",
          "ドコモ・ahamo"
        ],
        [
          "違約金補填キャンペーン",
          "あり（要確認）",
          "あり（要確認）",
          "あり（要確認）"
        ],
        [
          "工事費実質無料",
          "条件付きあり",
          "条件付きあり",
          "条件付きあり"
        ]
      ]
    },
    {
      "type": "paragraph",
      "text": "速度面ではNURO光が頭一つ抜けており、特に複数台のデバイスを同時接続する家庭や、オンラインゲーム・4K動画を頻繁に使う環境では体感差が出やすいです。auひかりはau・UQ mobileユーザーに最大**1,100円/月**のスマホセット割があり、スマホ料金込みのトータルコストで選ぶと有力な選択肢になります。ドコモ光はdocomoユーザーなら最大**1,100円/月**の割引があるほか、フレッツ光からの乗り換えなら**工事不要（事業者変更）**で移行できる点が便利です。"
    },
    {
      "type": "ranking_cta",
      "rankIndex": 1
    },
    {
      "type": "heading2",
      "text": "乗り換えの手順と各ステップで注意すべきこと"
    },
    {
      "type": "paragraph",
      "text": "流れを把握しておくと、「解約してから開通まで回線が使えない」という事態を避けられます。乗り換え先の開通を確認してから現在の回線を解約するのが鉄則です。"
    },
    {
      "type": "steps",
      "items": [
        {
          "title": "現在の契約内容を確認する",
          "description": "更新月・違約金額・撤去工事の要否を確認する。スマホとのセット割を受けている場合、解約するとスマホ料金が上がる可能性があるため合わせて確認しておく。"
        },
        {
          "title": "乗り換え先に申し込む",
          "description": "違約金補填キャンペーンの有無・適用条件・申請期限を必ずチェックしてから申し込む。工事日は混み合う時期に1〜2か月待ちになることもあるため、早めに予約を入れる。"
        },
        {
          "title": "新回線の開通を確認する",
          "description": "工事完了後、実際に通信できることを確認する。ルーターの設定変更が必要な場合があるため、開通サポートを活用すると安心。"
        },
        {
          "title": "現在の回線を解約する",
          "description": "新回線が問題なく使えることを確認してから解約手続きを行う。光コラボ→独自回線の場合はONUやルーターなどのレンタル機器の返却が必要。撤去工事が必要な場合は日程調整も忘れずに。"
        },
        {
          "title": "違約金補填の申請をする",
          "description": "乗り換え先のキャンペーンで補填を受ける場合、解約時の明細書が必要になることが多い。申請期限（申し込みから○か月以内など）があるため、解約後すぐに手続きを進める。"
        }
      ]
    },
    {
      "type": "heading2",
      "text": "よくある質問"
    },
    {
      "type": "paragraph",
      "text": "**Q: 更新月がいつかわからない場合はどうすればいい？**\nA: 契約書または各社マイページで確認できます。わからない場合はカスタマーサポートに電話すると即答してもらえます。契約開始から2〜3年目のタイミングが更新月になっているケースが多いです。"
    },
    {
      "type": "paragraph",
      "text": "**Q: 違約金補填キャンペーンはいくらまで補填してもらえる？**\nA: 各社・時期によって異なりますが、NURO光では最大**20,000円**程度の補填キャンペーンを実施していることがあります。申し込みページで最新の条件を確認するのが確実です。"
    },
    {
      "type": "paragraph",
      "text": "**Q: 光コラボからNURO光に乗り換える場合、インターネットが使えない期間はある？**\nA: NURO光は独自回線のため新規工事が必要で、工事完了まで現回線と並行利用することになります。現回線の解約は開通後に行えばよいため、==空白期間（ネットが使えない期間）は基本的に生じません==。"
    },
    {
      "type": "paragraph",
      "text": "**Q: 賃貸マンションでも乗り換えできる？**\nA: 可能ですが、NURO光やauひかりのような独自回線は建物オーナーの許可と対応状況の確認が必要です。光コラボ間の事業者変更（ドコモ光→ソフトバンク光など）なら工事不要のため、賃貸でもスムーズに乗り換えられます。"
    },
    {
      "type": "heading2",
      "text": "まとめ：乗り換えで損しないために"
    },
    {
      "type": "paragraph",
      "text": "光回線の乗り換えで損を避けるポイントは、**更新月の確認・違約金補填キャンペーンの活用・開通後に現回線を解約する順番**の3点に集約されます。これを押さえれば、実質的な費用負担をゼロに近づけることは十分に現実的です。"
    },
    {
      "type": "paragraph",
      "text": "乗り換え先として最もバランスが取れているのは**NURO光**です。実測平均**897Mbps**の速度と月額**5,200円〜**のコスト、そして乗り換え費用を補填するキャンペーンの充実度を総合すると、「速くて、安くて、移行しやすい」という3条件をまとめて満たしています。現在の回線に不満があるなら、まずNURO光のエリアと最新キャンペーンを確認してみることをおすすめします。"
    },
    {
      "type": "ranking_cta",
      "rankIndex": 0
    }
  ]
}