{
  "slug": "nuro-vs-au",
  "title": "NURO光vsauひかり どっちがいい？2026年最新比較",
  "excerpt": "料金・速度・エリア・サポートを徹底比較。結論はNURO光一択の理由を解説。",
  "category": "比較",
  "categoryColor": "orange",
  "emoji": "🔍",
  "publishedAt": "2026-03-25",
  "content": [
    {
      "type": "callout",
      "emoji": "📋",
      "text": "この記事でわかること\n・NURO光とauひかりの料金・速度・エリアの違い\n・どちらを選ぶべきか、状況別の結論\n・今月限定のお得なキャンペーン情報"
    },
    {
      "type": "heading2",
      "text": "結論：ほとんどの人にはNURO光がおすすめ"
    },
    {
      "type": "paragraph",
      "text": "NURO光とauひかりを比較した結果、==エリアが対応していればNURO光一択==です。理由は明確で、**実測平均897Mbps**という業界トップクラスの通信速度を、月額5,200円（戸建て）という競争力のある料金で提供しているからです。auひかりも悪い選択肢ではありませんが、速度・キャンペーン還元の両面でNURO光に一歩譲ります。"
    },
    {
      "type": "paragraph",
      "text": "ただし、NURO光は提供エリアが首都圏・関西・九州など**一部地域に限定**されています。エリア外の場合はauひかりが有力な次点候補です。まず自分のエリアを確認することが、回線選びの第一歩です。"
    },
    {
      "type": "ranking_cta",
      "rankIndex": 0
    },
    {
      "type": "heading2",
      "text": "料金比較：NURO光・auひかり・ドコモ光"
    },
    {
      "type": "paragraph",
      "text": "月額料金だけを見るとauひかりが安く見えますが、**キャンペーン適用後の実質負担額**で比べるとNURO光が最もお得になるケースが多いです。NURO光は現在、最大**60,000円キャッシュバック**や工事費無料などの入会特典を提供しており、長期利用での総コストを大幅に抑えられます。"
    },
    {
      "type": "table",
      "headers": [
        "項目",
        "NURO光",
        "auひかり",
        "ドコモ光"
      ],
      "rows": [
        [
          "月額料金（戸建て）",
          "5,200円",
          "5,610円〜",
          "5,720円〜"
        ],
        [
          "月額料金（マンション）",
          "2,090円〜",
          "4,180円〜",
          "4,400円〜"
        ],
        [
          "最大通信速度",
          "2Gbps",
          "1Gbps",
          "1Gbps"
        ],
        [
          "初期キャンペーン",
          "最大60,000円CB",
          "最大40,000円CB",
          "最大20,000円CB"
        ],
        [
          "工事費",
          "無料（キャンペーン）",
          "無料（キャンペーン）",
          "無料（キャンペーン）"
        ],
        [
          "提供エリア",
          "主要都市部",
          "全国（auエリア）",
          "全国（NTT回線）"
        ]
      ]
    },
    {
      "type": "paragraph",
      "text": "マンション向けプランでは、NURO光の**月額2,090円〜**というプランは他社と比べて圧倒的なコスパです。auひかりのマンションプランは4,180円〜と倍近い差があります。集合住宅に住んでいてNURO光のエリア内であれば、選ばない理由がほとんどありません。"
    },
    {
      "type": "heading2",
      "text": "速度比較：NURO光の2Gbpsは本物か"
    },
    {
      "type": "paragraph",
      "text": "カタログスペックでは、NURO光が**最大2Gbps**、auひかりとドコモ光が最大1Gbpsです。重要なのは「最大速度」ではなく**実際に出る速度**ですが、みんなのネット回線速度（みんそく）のデータでもNURO光は平均897Mbpsを記録しており、auひかりの平均約450Mbpsを大きく上回っています。"
    },
    {
      "type": "bar_chart",
      "title": "平均実測速度比較（下り）",
      "items": [
        {
          "label": "NURO光",
          "value": 897,
          "unit": "Mbps",
          "color": "bg-orange-400"
        },
        {
          "label": "auひかり",
          "value": 452,
          "unit": "Mbps",
          "color": "bg-blue-400"
        },
        {
          "label": "ドコモ光",
          "value": 381,
          "unit": "Mbps",
          "color": "bg-red-400"
        }
      ]
    },
    {
      "type": "paragraph",
      "text": "この速度差が生まれる背景には、NURO光が**独自の2コアケーブル（NURO独自回線）**を敷設していることがあります。NTTの既存回線を借りているauひかり・ドコモ光と異なり、設備から自社で管理しているため、混雑しにくく安定した速度が出やすいのです。4K動画・オンラインゲーム・テレワークを頻繁に使う人にとって、この差は体感レベルで感じられます。"
    },
    {
      "type": "heading2",
      "text": "エリア：NURO光の提供範囲を必ず確認"
    },
    {
      "type": "paragraph",
      "text": "NURO光の唯一の弱点が**提供エリアの狭さ**です。現在は東京・神奈川・千葉・埼玉・愛知・大阪・兵庫・福岡などの主要都市圏が中心で、地方の一部エリアでは利用できません。一方、auひかりはau（KDDI）のネットワークを活用しており、全国的にカバーしています。"
    },
    {
      "type": "list",
      "items": [
        "**NURO光が使えるなら**：迷わずNURO光を選ぶ",
        "**NURO光エリア外・auスマホユーザーなら**：auひかりでセット割を活用",
        "**ドコモユーザーでエリア外なら**：ドコモ光でスマホとまとめて割引",
        "**エリア問わず全国対応を優先するなら**：auひかりまたはドコモ光"
      ]
    },
    {
      "type": "ranking_cta",
      "rankIndex": 1
    },
    {
      "type": "heading2",
      "text": "スマホとのセット割：auひかりはauユーザーに有利"
    },
    {
      "type": "paragraph",
      "text": "auひかりはauスマホとのセット契約で、スマホ料金が**月額最大1,100円割引**になる「auスマートバリュー」が適用されます。家族でauスマホを複数台持っている場合、この割引は無視できません。一方、NURO光にはスマホとのセット割引制度がなく、この点ではauひかりに軍配が上がります。"
    },
    {
      "type": "paragraph",
      "text": "ただし、==スマホ割引を加味してもNURO光の速度・料金優位性が上回るケースが多い==です。たとえばNURO光マンションプラン（月額2,090円）とauひかりマンションプラン（月額4,180円）の差額は月2,090円。auスマートバリューの割引1,100円を差し引いても、**月990円以上NURO光が安い**計算になります。"
    },
    {
      "type": "heading2",
      "text": "工事・開通までの期間"
    },
    {
      "type": "paragraph",
      "text": "NURO光は独自回線の敷設が必要なため、**工事が2回に分かれる**（宅外工事＋宅内工事）ことがあります。開通まで最短2週間〜最大2ヶ月程度かかるケースもあり、「すぐにネットを使いたい」人には注意が必要です。auひかりはNTT回線を利用するため、工事は基本1回で**最短2〜3週間**での開通が多いです。"
    },
    {
      "type": "list",
      "items": [
        "**急ぎで開通させたい人**：auひかりの方がやや有利",
        "**開通まで数週間待てる人**：NURO光を選ぶ価値は十分にある",
        "工事費はどちらも現在のキャンペーンで**無料**になっている"
      ]
    },
    {
      "type": "heading2",
      "text": "カスタマーサポートの評判"
    },
    {
      "type": "paragraph",
      "text": "auひかりはKDDIの大規模なサポート体制があり、電話・チャット・店頭（auショップ）と**複数の窓口**でサポートを受けられます。NURO光はSONYグループのNUROが運営しており、電話サポートの繋がりにくさが一部で指摘されています。ただし、**公式チャットサポートは24時間対応**しており、深夜のトラブルにも対処できます。"
    },
    {
      "type": "paragraph",
      "text": "実際の口コミを見ると、auひかりは「au店舗で直接相談できて安心」という声が多く、NURO光は「速度には満足しているが電話が繋がりにくい」という声が一部あります。サポートを重視するならauひかりがやや優位ですが、**速度・料金の優位性を考えると、ほとんどのユーザーにはNURO光の方がトータルで満足度が高い**です。"
    },
    {
      "type": "heading2",
      "text": "こんな人にはNURO光、こんな人にはauひかり"
    },
    {
      "type": "list",
      "items": [
        "**NURO光がおすすめの人**：提供エリア内に住んでいる／速度を最優先したい／マンション住まいでコストを抑えたい／オンラインゲーム・4K配信をよく使う",
        "**auひかりがおすすめの人**：NURO光のエリア外に住んでいる／auスマホを複数台利用している／店頭サポートを重視する／早期開通を急いでいる",
        "**ドコモ光がおすすめの人**：ドコモスマホユーザーでNURO光エリア外／地方在住でエリアカバー率を重視する"
      ]
    },
    {
      "type": "ranking_cta",
      "rankIndex": 0
    },
    {
      "type": "heading2",
      "text": "まとめ：迷っているならNURO光を申し込む"
    },
    {
      "type": "paragraph",
      "text": "NURO光とauひかりを料金・速度・エリア・サポートで比較しました。==エリアが対応していれば、NURO光が最良の選択です==。**実測平均897Mbps**の速度、マンションなら月2,090円〜の料金、最大60,000円のキャッシュバックと、選ばない理由が見当たりません。auひかりはNURO光エリア外またはauスマホをまとめて割引したい場合の有力な次点です。"
    },
    {
      "type": "paragraph",
      "text": "今月のNURO光キャンペーンは**期間限定**で大型キャッシュバックが提供されています。来月以降は条件が変わる可能性があるため、申し込みは今月中に済ませることを強くおすすめします。まずは公式サイトでエリア確認を行い、対応していればそのまま申し込みまで完結できます。"
    }
  ]
}