{
  "slug": "nuro-hikari-campaign-cashback-2026",
  "title": "NURO光キャンペーン・キャッシュバック2026年最新情報",
  "excerpt": "NURO光の2026年最新キャンペーンとキャッシュバック情報をわかりやすく解説。",
  "category": "お得情報",
  "categoryColor": "orange",
  "emoji": "💰",
  "publishedAt": "2026-03-25",
  "content": [
    {
      "type": "callout",
      "emoji": "📋",
      "text": "この記事でわかること\n・NURO光の2026年最新キャンペーン内容\n・キャッシュバックをもらう条件と受け取り方\n・他社と比べてNURO光がお得な理由\n・申し込む前に確認しておくべきポイント"
    },
    {
      "type": "heading2",
      "text": "2026年のNURO光は「速さ」と「お得さ」が両立している"
    },
    {
      "type": "paragraph",
      "text": "NURO光は現在、==最大2Gbpsの高速回線==と充実したキャッシュバックキャンペーンを同時に提供している数少ない光回線サービスです。2026年3月時点の公式キャンペーンでは、**新規申し込みで最大30,000円相当のキャッシュバック**が受け取れる特典が展開されています。月額料金の安さだけでなく、初期費用の実質負担をゼロに近づけられる点が、他社との大きな差別化ポイントになっています。"
    },
    {
      "type": "paragraph",
      "text": "回線速度の実測値でも、NURO光は**平均897Mbps**（みんなのネット回線速度調べ）を記録しており、主要光回線の中でトップクラスの数値を維持しています。速度とコストパフォーマンスの両方を重視するなら、NURO光は有力な選択肢です。"
    },
    {
      "type": "ranking_cta",
      "rankIndex": 0
    },
    {
      "type": "heading2",
      "text": "2026年3月時点のNURO光キャンペーン一覧"
    },
    {
      "type": "paragraph",
      "text": "現在展開中のキャンペーンは大きく3種類あります。それぞれ適用条件が異なるため、自分の状況に合ったものを確認しておくことが重要です。"
    },
    {
      "type": "list",
      "items": [
        "**新規申し込みキャッシュバック**：公式サイトから申し込むと最大30,000円のキャッシュバックが受け取れる。開通から一定期間後に指定口座へ振り込まれる形式",
        "**工事費実質無料キャンペーン**：通常19,800円かかる工事費が、月額割引の形で実質無料になる。途中解約しなければ総支払額はゼロ",
        "**ひかりTVセット割**：ひかりTVと同時申し込みで月額550円割引。動画配信サービスを使う家庭に向いている組み合わせ"
      ]
    },
    {
      "type": "heading2",
      "text": "キャッシュバックを確実に受け取るための3つのポイント"
    },
    {
      "type": "paragraph",
      "text": "キャッシュバックはただ申し込むだけでは受け取れないケースがあります。受け取り忘れや条件未達を防ぐために、以下の3点を事前に押さえておくと安心です。"
    },
    {
      "type": "list",
      "items": [
        "**申し込み窓口を確認する**：キャッシュバックの金額や条件は「公式サイト」「代理店サイト」「家電量販店」によって異なる。==最も高額なキャッシュバックは代理店経由の公式キャンペーンページ経由が多い==",
        "**受け取り期限を把握する**：多くのキャンペーンでは開通後6〜12カ月以内にWebフォームや電話での申請が必要。期限を過ぎると自動的に失効する",
        "**最低利用期間を守る**：2年以内に解約すると違約金が発生し、キャッシュバックが相殺されるケースがある。長期利用前提で申し込むのが基本"
      ]
    },
    {
      "type": "heading2",
      "text": "NURO光・auひかり・ドコモ光のキャンペーン比較"
    },
    {
      "type": "paragraph",
      "text": "主要3社のキャンペーン内容を比較すると、NURO光の強みがより明確になります。特に**回線速度×キャッシュバック金額の総合評価**ではNURO光が頭ひとつ抜けています。"
    },
    {
      "type": "table",
      "headers": [
        "項目",
        "NURO光",
        "auひかり",
        "ドコモ光"
      ],
      "rows": [
        [
          "最大通信速度",
          "2Gbps",
          "1Gbps",
          "1Gbps"
        ],
        [
          "実測平均速度",
          "約897Mbps",
          "約550Mbps",
          "約380Mbps"
        ],
        [
          "月額料金（戸建て）",
          "5,200円",
          "5,610円",
          "5,720円"
        ],
        [
          "キャッシュバック上限",
          "最大30,000円",
          "最大40,000円",
          "最大20,000円"
        ],
        [
          "工事費実質無料",
          "あり",
          "あり",
          "あり"
        ],
        [
          "独自回線",
          "あり（速度安定）",
          "あり（速度安定）",
          "なし（NTT回線共用）"
        ]
      ]
    },
    {
      "type": "paragraph",
      "text": "auひかりはキャッシュバック金額ではNURO光を上回りますが、**月額料金がNURO光より約400円高く**、2年間の差額はキャッシュバック差額を上回ります。総支払額で比較するとNURO光の方が割安になるケースがほとんどです。ドコモ光はドコモスマホとのセット割が魅力ですが、NTT回線を共用するため混雑時間帯の速度低下が起きやすい点は考慮が必要です。"
    },
    {
      "type": "ranking_cta",
      "rankIndex": 0
    },
    {
      "type": "heading2",
      "text": "NURO光が特に向いている人・向いていない人"
    },
    {
      "type": "paragraph",
      "text": "どんな回線にも向き不向きがあります。申し込む前に自分の状況と照らし合わせておくと、後悔のない選択につながります。"
    },
    {
      "type": "list",
      "items": [
        "**向いている人**：動画配信・オンラインゲーム・テレワークなど、==常時高速な回線が必要な用途==がある人",
        "**向いている人**：NURO光の提供エリア（東京・神奈川・千葉・埼玉・大阪など主要都市圏）に住んでいる人",
        "**向いている人**：初期費用を抑えつつ、長期的に安い料金で使い続けたい人",
        "**向いていない人**：NURO光のエリア外に居住している人（エリア確認は公式サイトで即日確認可能）",
        "**向いていない人**：ソフトバンクスマホを使っており、スマホとのセット割を最優先にしたい人（その場合はSoftBank光が候補になる）"
      ]
    },
    {
      "type": "heading2",
      "text": "工事の流れと開通までの期間"
    },
    {
      "type": "paragraph",
      "text": "NURO光は独自の光ファイバーを引き込むため、開通工事が**2回**必要です。1回目は宅内工事（所要時間2〜3時間）、2回目は屋外工事（NTTの設備接続）で、それぞれ別日程で行われます。申し込みから開通まで**平均3〜6週間**かかるため、引っ越し予定がある場合は早めに申し込んでおくと安心です。"
    },
    {
      "type": "list",
      "items": [
        "**STEP 1**：公式サイトまたは代理店ページから申し込み（5〜10分で完了）",
        "**STEP 2**：1回目の宅内工事日を調整・実施（申し込みから2〜4週間後が目安）",
        "**STEP 3**：2回目の屋外工事実施（1回目から1〜2週間後が目安）",
        "**STEP 4**：開通確認・ONU（光回線終端装置）設置完了でインターネット利用開始"
      ]
    },
    {
      "type": "heading2",
      "text": "よくある質問"
    },
    {
      "type": "paragraph",
      "text": "**Q：集合住宅（マンション）でもNURO光は使えますか？**\nA：使えます。NURO光 for マンションというプランがあり、月額料金は戸建てより安い**2,090円〜**（マンションの設備状況による）。ただし管理組合の許可が必要なケースがあるため、事前に管理会社へ確認しておくと安心です。"
    },
    {
      "type": "paragraph",
      "text": "**Q：キャッシュバックはいつ振り込まれますか？**\nA：多くのキャンペーンでは==開通から6カ月後==を目安に申請手続きが案内され、申請後1〜2カ月以内に指定口座へ振り込まれます。申請期限を過ぎると失効するため、開通時にスケジュールをカレンダーに登録しておくことをおすすめします。"
    },
    {
      "type": "paragraph",
      "text": "**Q：引っ越しするとどうなりますか？**\nA：NURO光のエリア内への引っ越しであれば、**移転工事で継続利用が可能**です。移転工事費は別途かかりますが、再契約扱いにはならず違約金は発生しません。エリア外への引っ越しの場合は解約となり、残存する契約期間によって違約金が発生することがあります。"
    },
    {
      "type": "paragraph",
      "text": "**Q：IPv6に対応していますか？**\nA：対応しています。NURO光はNUROが独自に構築したIPv6（次世代のインターネット通信規格）ネットワークを使用しており、混雑しやすいプロバイダ網を迂回できる構造になっています。これが**夜間の速度低下が少ない理由**のひとつです。"
    },
    {
      "type": "ranking_cta",
      "rankIndex": 0
    },
    {
      "type": "heading2",
      "text": "まとめ：2026年にNURO光を選ぶ理由"
    },
    {
      "type": "paragraph",
      "text": "2026年現在、光回線を新規契約するうえで==NURO光は速度・料金・キャンペーンの三拍子が揃った選択肢==です。実測平均897Mbpsという数値は、動画配信もテレワークもストレスなくこなせる水準であり、最大30,000円のキャッシュバックと工事費実質無料を組み合わせれば、初年度の実質負担を大幅に抑えることができます。"
    },
    {
      "type": "list",
      "items": [
        "**速度**：実測平均897Mbpsで主要光回線トップクラス",
        "**料金**：月額5,200円（戸建て）で主要3社の中で最安水準",
        "**キャンペーン**：最大30,000円キャッシュバック＋工事費実質無料",
        "**安定性**：独自回線×IPv6で混雑時間帯の速度低下が少ない",
        "**エリア**：東京・大阪をはじめ主要都市圏をカバー（公式サイトで即日確認可能）"
      ]
    },
    {
      "type": "paragraph",
      "text": "まずは公式サイトでエリア確認を済ませ、キャンペーンの適用条件を確認してから申し込む流れが、**最もお得に契約できるルート**です。キャンペーンの終了時期は予告なく変更されることがあるため、検討が固まった段階で早めに手続きを進めておくと確実です。"
    }
  ]
}