{
  "slug": "softbank-hikari-norikae-osusume-tejun-2026",
  "title": "ソフトバンク光乗り換え先おすすめ5選｜手順と費用2026",
  "excerpt": "ソフトバンク光からの乗り換え先5社を比較。手順・違約金・最適タイミングまで徹底解説します。",
  "category": "比較",
  "categoryColor": "orange",
  "emoji": "🔄",
  "publishedAt": "2026-04-27",
  "content": [
    {
      "type": "callout",
      "emoji": "📋",
      "text": "この記事でわかること：ソフトバンク光からの乗り換え先5社の料金・速度比較 / 違約金の金額と回避法 / 事業者変更・独自回線それぞれの手順 / スマホセット割を含む通信費トータルの最適化"
    },
    {
      "type": "heading2",
      "text": "【結論】ソフトバンク光からの乗り換え先はNURO光が最有力"
    },
    {
      "type": "paragraph",
      "text": "乗り換え先を結論から伝えると、==NURO光が最有力候補==です。実測平均下り約550Mbpsはソフトバンク光（約320Mbps）の約1.7倍、月額5,200円（戸建）はソフトバンク光より**520円安く**、最大45,000円キャッシュバックと他社違約金最大60,000円負担の特典が揃っています。NURO光のエリア外であれば、工事不要で乗り換えられる光コラボ3社が有力な代替策になります。"
    },
    {
      "type": "ranking_cta",
      "rankIndex": 0
    },
    {
      "type": "heading2",
      "text": "ソフトバンク光を乗り換えるべき3つの理由"
    },
    {
      "type": "paragraph",
      "text": "ソフトバンク光には「おうち割光セット」がありますが、スマホをワイモバイルや格安SIMに変更すると割引が縮小・消滅し、実質的なコストパフォーマンスが大きく下がります。料金・速度・セット割の3点で見直しが必要な状況をまとめました。"
    },
    {
      "type": "list",
      "items": [
        "**料金の割高感**：おうち割光セット終了後の戸建月額5,720円は、光コラボ他社の最安級と比べて月900円以上高くなるケースがある",
        "**速度の伸び悩み**：IPv6高速ハイブリッド利用時でも実測平均下り約320Mbpsにとどまり、NURO光（約550Mbps）との差が広がっている",
        "**セット割の縮小リスク**：ワイモバイルや格安SIMへ変更するとおうち割が最大1,100円→最大1,650円に変わる場合もあるが、格安SIMでは割引が消滅し年間1万円以上の差が生じる"
      ]
    },
    {
      "type": "heading2",
      "text": "乗り換え先おすすめ5社を徹底比較【料金・速度・特典】"
    },
    {
      "type": "paragraph",
      "text": "スマホキャリア別に最適な組み合わせが異なります。ソフトバンク継続ならNURO光、ドコモユーザーはドコモ光、auユーザーはauひかり、格安SIM乗り換え予定ならGMOとくとくBB光が月額最安級でおすすめです。"
    },
    {
      "type": "table",
      "headers": [
        "回線名",
        "月額（戸建）",
        "実測平均下り",
        "主な特典・割引",
        "おすすめスマホ"
      ],
      "rows": [
        [
          "NURO光",
          "5,200円",
          "約550Mbps",
          "最大CB45,000円・違約金負担60,000円",
          "ソフトバンク"
        ],
        [
          "GMOとくとくBB光",
          "4,818円",
          "非公開",
          "縛りなし・最大CB43,000円",
          "格安SIM全般"
        ],
        [
          "ドコモ光",
          "5,720円",
          "非公開",
          "セット割最大1,100円/月",
          "ドコモ"
        ],
        [
          "auひかり",
          "5,610円",
          "非公開",
          "auスマートバリュー最大1,100円/月",
          "au/UQ mobile"
        ],
        [
          "楽天ひかり",
          "4,180円（1年無料）",
          "非公開",
          "楽天モバイルセット割110円/月",
          "楽天モバイル"
        ]
      ]
    },
    {
      "type": "heading2",
      "text": "【最有力】NURO光をおすすめする5つの根拠"
    },
    {
      "type": "paragraph",
      "text": "NURO光は独自の2Gbps回線を持ち、混雑しやすい夜間帯でも**実測平均下り約550Mbps**を維持しています。ソフトバンク光ユーザーにとって特に大きいのは、ソフトバンクスマホをそのまま使いながらおうち割光セット（最大1,100円/月）が継続適用できる点です。"
    },
    {
      "type": "list",
      "items": [
        "**速度**：下り最大2Gbpsの独自回線で実測約550Mbps、ソフトバンク光比で約1.7倍",
        "**料金**：月額5,200円（戸建）はソフトバンク光より月520円安く、2年で12,480円の節約",
        "**初期費用**：工事費44,000円が36ヶ月分割で実質無料、解約しなければ負担ゼロ",
        "**乗り換え特典**：最大45,000円キャッシュバック＋他社違約金最大60,000円負担で初期コストを相殺"
      ]
    },
    {
      "type": "callout",
      "emoji": "🎁",
      "text": "NURO光の他社違約金負担（最大60,000円）はキャンペーン終了期限があります。乗り換えを検討中なら早めに公式サイトで条件を確認しておくのがおすすめです。"
    },
    {
      "type": "ranking_cta",
      "rankIndex": 0
    },
    {
      "type": "heading2",
      "text": "NURO光エリア外の場合のおすすめ乗り換え先3社"
    },
    {
      "type": "paragraph",
      "text": "NURO光は提供エリアが主要都市に限られます。エリア外の場合は、フレッツ回線を使った光コラボに事業者変更するのがもっとも手間が少ない方法です。以下の3社が特に評価が高くなっています。"
    },
    {
      "type": "list",
      "items": [
        "**GMOとくとくBB光（戸建4,818円）**：縛りなし・違約金なしで格安SIMユーザーに最適。最大キャッシュバック43,000円も魅力",
        "**ドコモ光（戸建5,720円）**：ドコモスマホとのセット割で月最大1,100円引き、実質月額はソフトバンク光と同水準以下になるケースも",
        "**auひかり（戸建5,610円）**：独自回線による高速通信とauスマートバリューで最大1,100円/月割引、au・UQ mobileユーザーに有力"
      ]
    },
    {
      "type": "heading2",
      "text": "ソフトバンク光の解約にかかる違約金・費用と回避法"
    },
    {
      "type": "paragraph",
      "text": "乗り換えコストを正確に把握することが、最適なタイミングを選ぶ第一歩です。**2022年7月以降の契約**は違約金が大幅に下がっており、更新月を狙えばゼロにできます。"
    },
    {
      "type": "definition_list",
      "items": [
        {
          "term": "違約金（2022年7月以降の契約）",
          "description": "戸建5,720円・マンション4,180円（月額1ヶ月分相当）。更新月3ヶ月間は違約金0円。"
        },
        {
          "term": "違約金（2022年7月より前の契約）",
          "description": "10,450円。更新月でも解約金が発生する場合があるため、契約書で確認を。"
        },
        {
          "term": "工事費残債",
          "description": "分割払い中の場合は残額を一括精算。開通から3年以内の解約で発生しやすい。"
        },
        {
          "term": "レンタル機器（光BBユニット等）",
          "description": "解約後、指定の方法で返却が必要。返却しない場合は機器代金が請求される。"
        },
        {
          "term": "更新月の期間",
          "description": "契約満了月・翌月・翌々月の3ヶ月間。My SoftBankまたは電話（157）で確認可能。"
        }
      ]
    },
    {
      "type": "heading2",
      "text": "【図解】乗り換え手順を事業者変更・独自回線別に解説"
    },
    {
      "type": "paragraph",
      "text": "乗り換えには「事業者変更（光コラボ→光コラボ）」と「独自回線への切替」の2パターンがあります。工事不要で最短1〜2週間で切り替わる事業者変更と、開通工事が必要だが高速な独自回線への切替、それぞれの手順を確認しておきましょう。"
    },
    {
      "type": "heading3",
      "text": "パターン①：事業者変更（GMOとくとくBB光・ドコモ光など光コラボへ）"
    },
    {
      "type": "steps",
      "items": [
        {
          "title": "事業者変更承諾番号を取得する",
          "description": "My SoftBank・電話（0800-111-2009）・ソフトバンクショップで取得。手数料は0円〜3,300円（窓口による）。有効期限は発行から15日間。"
        },
        {
          "title": "乗り換え先に申し込む",
          "description": "取得した承諾番号を入力して申し込む。切替日を更新月初日に合わせると二重払いを最小化できる。"
        },
        {
          "title": "自動切替・機器返却",
          "description": "工事不要で約1〜2週間後に自動切替。切替後はレンタル機器（光BBユニット等）を期限内に返却する。"
        }
      ]
    },
    {
      "type": "heading3",
      "text": "パターン②：独自回線への切替（NURO光・auひかりなど）"
    },
    {
      "type": "steps",
      "items": [
        {
          "title": "乗り換え先に申し込む",
          "description": "NURO光やauひかりの公式サイトから申し込む。他社違約金負担キャンペーンへの申請もこのタイミングで確認する。"
        },
        {
          "title": "開通工事を受ける",
          "description": "工事完了まで1〜2ヶ月かかる。期間中はレンタルWiFiでつなぎを確保しておくと安心。"
        },
        {
          "title": "ソフトバンク光を解約する",
          "description": "新回線が開通したことを確認してからソフトバンク光を解約する。解約前に違約金と工事費残債を必ず確認すること。"
        },
        {
          "title": "レンタル機器を返却する",
          "description": "解約後に届く返却案内に従い、光BBユニット等を期限内に返送する。"
        }
      ]
    },
    {
      "type": "heading2",
      "text": "乗り換えの最適タイミングは「更新月の2ヶ月前」"
    },
    {
      "type": "paragraph",
      "text": "独自回線（NURO光・auひかり）は開通まで1〜2ヶ月かかるため、**更新月の2ヶ月前に申し込む**のがベストです。新回線が開通したタイミングでちょうど違約金ゼロの更新月と重なり、余分なコストをかけずにスムーズに切り替えられます。"
    },
    {
      "type": "callout",
      "emoji": "📅",
      "text": "更新月はMy SoftBankの「ご契約内容の確認・変更」または電話（157）で確認できます。契約満了月・翌月・翌々月の3ヶ月間が違約金0円の更新月です。まずここから確認するのがおすすめです。"
    },
    {
      "type": "heading2",
      "text": "スマホセット割の再設計｜乗り換え後のベストな組み合わせ"
    },
    {
      "type": "paragraph",
      "text": "光回線の乗り換えと同時にスマホプランを見直すと、通信費を月2,000円以上圧縮できるケースもあります。現在のスマホキャリアに合わせて最適な組み合わせを選びましょう。"
    },
    {
      "type": "list",
      "items": [
        "**ソフトバンク継続 → NURO光**：おうち割光セット（最大1,100円/月）がそのまま継続。速度アップ＋月額値下げの両取りが可能",
        "**ワイモバイルへ変更予定 → GMOとくとくBB光**：ワイモバイルはソフトバンク光と親和性が高いが、GMOとくとくBB光のほうが月額安く縛りもなし",
        "**格安SIM（ahamo・povo・LINEMO等）→ 月額最安の光コラボ**：セット割が不要なため純粋に月額が安い回線を選ぶのが正解。GMOとくとくBB光（戸建4,818円）が候補筆頭"
      ]
    },
    {
      "type": "heading2",
      "text": "よくある質問（FAQ）"
    },
    {
      "type": "definition_list",
      "items": [
        {
          "term": "ソフトバンク光から乗り換えるとき違約金は乗り換え先が負担してくれますか？",
          "description": "NURO光は他社違約金を最大60,000円まで負担するキャンペーンを実施中です（条件あり・期間限定）。GMOとくとくBB光やドコモ光でも一部負担キャンペーンがある場合があるため、申し込み前に公式サイトで確認してください。"
        },
        {
          "term": "ソフトバンク光からNURO光への乗り換えでネットが使えない空白期間はどのくらいですか？",
          "description": "NURO光の開通工事後にソフトバンク光を解約する手順を踏めば、空白期間をゼロにできます。工事完了の確認後に解約手続きをする順番を守ることが重要です。工事期間中のつなぎにはレンタルWiFiの活用がおすすめです。"
        },
        {
          "term": "ソフトバンクのスマホをそのまま使いたい場合、おうち割は乗り換え後も適用されますか？",
          "description": "NURO光への乗り換え後も、ソフトバンクのスマホ回線を継続していれば「おうち割光セット」（最大1,100円/月）は引き続き適用されます。ただし光回線がNURO光に変わるため、NURObB（ソフトバンク系プロバイダ）との契約が条件になる場合があります。申し込み前に確認してください。"
        },
        {
          "term": "ソフトバンク光の事業者変更承諾番号はどこで取得できますか？",
          "description": "My SoftBankのウェブサイト・ソフトバンクショップ・電話（0800-111-2009）の3か所で取得できます。My SoftBankからのオンライン取得なら手数料0円で即日発行が可能です。ショップや電話窓口では3,300円の手数料がかかる場合があります。"
        },
        {
          "term": "乗り換え時にソフトバンク光のレンタル機器（光BBユニットなど）はいつまでに返却すればいいですか？",
          "description": "解約後に届く返却案内に記載された期限（通常は解約月の翌月末頃）までに返却が必要です。期限を過ぎると機器代金が請求されます。返却用伝票が同封されているため、指定の方法で速やかに返送してください。"
        }
      ]
    },
    {
      "type": "callout",
      "emoji": "✅",
      "text": "まとめ：速度・料金・特典の3拍子が揃うNURO光がソフトバンク光からの乗り換え先として最もおすすめです。ソフトバンクスマホを継続しながらおうち割も維持できるため、セット割を失わずにコストを下げられます。まずは[NURO光の公式サイト](https://px.a8.net/svt/ejp?a8mat=2BJ8HV+6NXPKI+2VMU+64C3M)でエリアと最新キャンペーンを確認してみてください。"
    },
    {
      "type": "ranking_cta",
      "rankIndex": 0
    },
    {
      "type": "related_articles",
      "items": [
        {
          "slug": "hikari-kaisen-norikae-tejun-timing-guide",
          "title": "光回線の乗り換え手順とベストタイミング【2026年4月版】"
        },
        {
          "slug": "hikari-kaisen-iyakukin-futan-campaign-hikaku",
          "title": "【2026年4月】光回線の違約金負担キャンペーン比較"
        },
        {
          "slug": "hikari-kaisen-norikae-kikan-kuuhaku-zero-schedule",
          "title": "光回線の乗り換え期間は？空白ゼロの切り替え術"
        }
      ]
    }
  ],
  "thumbnail": "/thumbnails/softbank-hikari-norikae-osusume-tejun-2026.jpg"
}